elements/__init__.py
elements/cli/__init__.py
elements/cli/ts.py
elements/cli/commands/__init__.py
elements/cli/commands/algorithm.py
elements/cli/commands/algorithm_computation.py
elements/cli/commands/algorithm_config.py
elements/cli/commands/algorithm_version.py
elements/cli/commands/analysis.py
elements/cli/commands/analysis_computation.py
elements/cli/commands/analysis_config.py
elements/cli/commands/analysis_version.py
elements/cli/commands/aoi.py
elements/cli/commands/credit.py
elements/cli/commands/data.py
elements/cli/commands/environment.py
elements/cli/commands/imagery.py
elements/cli/commands/manifest.py
elements/cli/commands/permission.py
elements/cli/commands/tasks.py
elements/cli/commands/toi.py
elements/cli/commands/visualization.py
elements/cli/lib/__init__.py
elements/cli/lib/aliased_group.py
elements/cli/lib/utils.py
elements/cli/lib/workflow.py
elements/sdk/__init__.py
elements/sdk/elements_sdk.py
elements/sdk/api/__init__.py
elements/sdk/api/algorithm.py
elements/sdk/api/analysis.py
elements/sdk/api/aoi.py
elements/sdk/api/credit.py
elements/sdk/api/data.py
elements/sdk/api/filter.py
elements/sdk/api/order.py
elements/sdk/api/permission.py
elements/sdk/api/result.py
elements/sdk/api/tasking_order.py
elements/sdk/api/toi.py
elements/sdk/api/user.py
elements/sdk/api/visualization.py
elements/sdk/builder/__init__.py
elements/sdk/builder/algorithm.py
elements/sdk/builder/analysis.py
elements/sdk/builder/toi.py
elements/sdk/tools/__init__.py
elements/sdk/tools/io.py
elements/sdk/tools/sdk_support.py
privateer_elements_sdk-2026.1.20.dist-info/licenses/LICENSE
tests/integration/test_algorithm.py
tests/integration/test_algorithm_builder.py
tests/integration/test_analysis.py
tests/integration/test_analysis_builder.py
tests/integration/test_aoi.py
tests/integration/test_credit.py
tests/integration/test_data.py
tests/integration/test_permission.py
tests/integration/test_result.py
tests/integration/test_sdk_support.py
tests/integration/test_toi.py
tests/integration/test_visualization.py
privateer_elements_sdk-2026.1.20.dist-info/METADATA
privateer_elements_sdk-2026.1.20.dist-info/WHEEL
privateer_elements_sdk-2026.1.20.dist-info/entry_points.txt
privateer_elements_sdk-2026.1.20.dist-info/top_level.txt
privateer_elements_sdk-2026.1.20.dist-info/RECORD
